nomad_camels_driver_zurichinstruments_uhfli_600/__init__.py
nomad_camels_driver_zurichinstruments_uhfli_600/zurichinstruments_uhfli_600.py
nomad_camels_driver_zurichinstruments_uhfli_600/zurichinstruments_uhfli_600_ophyd.py
nomad_camels_driver_zurichinstruments_uhfli_600-0.1.0.dist-info/licenses/LICENSE.txt
nomad_camels_driver_zurichinstruments_uhfli_600-0.1.0.dist-info/METADATA
nomad_camels_driver_zurichinstruments_uhfli_600-0.1.0.dist-info/WHEEL
nomad_camels_driver_zurichinstruments_uhfli_600-0.1.0.dist-info/top_level.txt
nomad_camels_driver_zurichinstruments_uhfli_600-0.1.0.dist-info/RECORD
